agentsjson/core/__init__.py
agentsjson/core/executor.py
agentsjson/core/loader.py
agentsjson/core/models/__init__.py
agentsjson/core/models/auth.py
agentsjson/core/models/bundle.py
agentsjson/core/models/schema.py
agentsjson/core/models/tools.py
agentsjson/core/parsetools.py
agentsjson/core/utils.py
agentsjson_core-0.1.0.dist-info/METADATA
agentsjson_core-0.1.0.dist-info/WHEEL
agentsjson_core-0.1.0.dist-info/RECORD
