Metadata-Version: 2.3
Name: agentsjson-core
Version: 0.1.0
Summary: Core functionality for Agents.json Python implementation
License: BUSL-1.1
Author: Wildcard AI
Author-email: info@wildcard.ai
Requires-Python: >=3.8,<4.0
Classifier: License :: Other/Proprietary License
Classifier: Programming Language :: Python :: 3
Classifier: Programming Language :: Python :: 3.8
Classifier: Programming Language :: Python :: 3.9
Classifier: Programming Language :: Python :: 3.10
Classifier: Programming Language :: Python :: 3.11
Classifier: Programming Language :: Python :: 3.12
Classifier: Programming Language :: Python :: 3.13
Requires-Dist: pydantic (>=2.0.0,<3.0.0)
Requires-Dist: python-benedict (>=0.33.0,<0.34.0)
Requires-Dist: typing-extensions (>=4.0.0,<5.0.0)
